pandas_liteql/__init__.py
pandas_liteql/liteql.py
pandas_liteql-0.5.3.dist-info/LICENSE
pandas_liteql-0.5.3.dist-info/METADATA
pandas_liteql-0.5.3.dist-info/WHEEL
pandas_liteql-0.5.3.dist-info/top_level.txt
pandas_liteql-0.5.3.dist-info/RECORD
