Metadata-Version: 2.1
Name: pandas-liteql
Version: 0.5.3
Summary: A simple pandas extension that enables users to execute SQL statements against DataFrames using in-memory SQLite.
Author-email: forgineer <blake.phillips86@gmail.com>
License: MIT License
Project-URL: Homepage, https://github.com/forgineer/pandas-liteql
Project-URL: Documentation, https://github.com/forgineer/pandas-liteql
Project-URL: Repository, https://github.com/forgineer/pandas-liteql
Project-URL: Issues, https://github.com/forgineer/pandas-liteql/issues
Keywords: dataframe,pandas,sql,sqlite
Classifier: Development Status :: 7 - Inactive
Classifier: License :: OSI Approved :: MIT License
Classifier: Operating System :: OS Independent
Classifier: Intended Audience :: Developers
Classifier: Intended Audience :: Information Technology
Classifier: Topic :: Scientific/Engineering :: Information Analysis
Classifier: Programming Language :: Python :: 3.7
Classifier: Programming Language :: Python :: 3.8
Classifier: Programming Language :: Python :: 3.9
Classifier: Programming Language :: Python :: 3.10
Classifier: Programming Language :: Python :: 3.11
Classifier: Programming Language :: Python :: 3.12
Requires-Python: >=3.7
License-File: LICENSE
Requires-Dist: pandas >=1.3.5
Requires-Dist: sqlalchemy >=1.4.36
Provides-Extra: pypi_deploy
Requires-Dist: build ; extra == 'pypi_deploy'
Requires-Dist: twine ; extra == 'pypi_deploy'
